{
  "stats": {
    "suites": 1,
    "tests": 7,
    "passes": 7,
    "pending": 0,
    "failures": 0,
    "start": "2025-10-21T16:42:58.450Z",
    "end": "2025-10-21T16:43:36.825Z",
    "duration": 38375,
    "testsRegistered": 7,
    "passPercent": 100,
    "pendingPercent": 0,
    "other": 0,
    "hasOther": false,
    "skipped": 0,
    "hasSkipped": false
  },
  "results": [
    {
      "uuid": "15582cf2-a3c2-46f6-b7f3-66e80ce492a7",
      "title": "",
      "fullFile": "cypress/e2e/api/002 - API Integração Clientes/001 - API Ficha Profisssional/002.api-inclusao-ficha-erros-soap.cy.js",
      "file": "cypress/e2e/api/002 - API Integração Clientes/001 - API Ficha Profisssional/002.api-inclusao-ficha-erros-soap.cy.js",
      "beforeHooks": [],
      "afterHooks": [],
      "tests": [],
      "suites": [
        {
          "uuid": "d58f4515-5972-4e0f-a4d7-e64371ac87b3",
          "title": "Integração Clientes - API Inclusão de Ficha do Profissional - Validação de Erros",
          "fullFile": "",
          "file": "",
          "beforeHooks": [],
          "afterHooks": [],
          "tests": [
            {
              "title": "Validação de erro: Corpo da requisição (vazio)",
              "fullTitle": "Integração Clientes - API Inclusão de Ficha do Profissional - Validação de Erros Validação de erro: Corpo da requisição (vazio)",
              "timedOut": null,
              "duration": 1419,
              "state": "passed",
              "speed": "fast",
              "pass": true,
              "fail": false,
              "pending": false,
              "context": null,
              "code": "cy.api({\n  method: \"POST\",\n  url: url,\n  body: \"\",\n  failOnStatusCode: false\n}).then(r => {\n  const faultcode = r.body.match(/<faultcode>([\\s\\S]*?)<\\/faultcode>/)[1].trim();\n  const faultstring = r.body.match(/<faultstring>([\\s\\S]*?)<\\/faultstring>/)[1].trim();\n  expect(r.status).to.eq(500);\n  expect(faultcode).to.eq(\"SOAP-ENV:Client\");\n  expect(faultstring).to.eq(\"Bad Request\");\n});",
              "err": {},
              "uuid": "3daeeca4-d420-48ea-9655-cdb37593c84c",
              "parentUUID": "d58f4515-5972-4e0f-a4d7-e64371ac87b3",
              "isHook": false,
              "skipped": false
            },
            {
              "title": "Validação de erro: CNPJ do Cliente (vazio)",
              "fullTitle": "Integração Clientes - API Inclusão de Ficha do Profissional - Validação de Erros Validação de erro: CNPJ do Cliente (vazio)",
              "timedOut": null,
              "duration": 2920,
              "state": "passed",
              "speed": "fast",
              "pass": true,
              "fail": false,
              "pending": false,
              "context": null,
              "code": "const payloadModificado = soapPayload.replace(`<inc:cnpj_cliente>${cnpjCliente}</inc:cnpj_cliente>`, `<inc:cnpj_cliente></inc:cnpj_cliente>`);\ncy.api({\n  method: \"POST\",\n  url: url,\n  body: payloadModificado,\n  failOnStatusCode: false\n}).then(r => {\n  const faultcode = r.body.match(/<faultcode>([\\s\\S]*?)<\\/faultcode>/)[1].trim();\n  const faultstring = r.body.match(/<faultstring>([\\s\\S]*?)<\\/faultstring>/)[1].trim();\n  cy.log(r.body);\n  expect(r.status).to.eq(500);\n  expect(faultcode).to.eq(\"ns1:1\");\n  expect(faultstring).to.be.oneOf([\"CNPJ Cliente não informado ou XML Inválido\", \"O token informado não confere com o cnpj do cliente\"]);\n});",
              "err": {},
              "uuid": "76808a4c-733d-409c-a85c-8c1e56d6be99",
              "parentUUID": "d58f4515-5972-4e0f-a4d7-e64371ac87b3",
              "isHook": false,
              "skipped": false
            },
            {
              "title": "Validação de erro: CNPJ do Embarcador (vazio) ou (inválido)",
              "fullTitle": "Integração Clientes - API Inclusão de Ficha do Profissional - Validação de Erros Validação de erro: CNPJ do Embarcador (vazio) ou (inválido)",
              "timedOut": null,
              "duration": 5096,
              "state": "passed",
              "speed": "medium",
              "pass": true,
              "fail": false,
              "pending": false,
              "context": null,
              "code": "const cnpjs = [\"\", \"abc\"];\nconst cnpj_aleatorio = cnpjs[Math.floor(Math.random() * cnpjs.length)];\nconst payloadModificado = soapPayload.replace(`<inc:cnpj_embarcador>${cnpjCliente}</inc:cnpj_embarcador>`, `<inc:cnpj_embarcador>${cnpj_aleatorio}</inc:cnpj_embarcador>`);\ncy.api({\n  method: \"POST\",\n  url: url,\n  body: payloadModificado,\n  failOnStatusCode: false\n}).then(r => {\n  const faultcode = r.body.match(/<faultcode>([\\s\\S]*?)<\\/faultcode>/)[1].trim();\n  const faultstring = r.body.match(/<faultstring>([\\s\\S]*?)<\\/faultstring>/)[1].trim();\n  expect(r.status).to.eq(500);\n  expect(faultcode).to.eq(\"ns1:1\");\n  expect(faultstring).to.be.oneOf([\"CNPJ Embarcador não informado\", \"O CNPJ Embarcador não está cadastrado\"]);\n});",
              "err": {},
              "uuid": "c4de8bba-3816-4b0f-9b4f-a003d311791f",
              "parentUUID": "d58f4515-5972-4e0f-a4d7-e64371ac87b3",
              "isHook": false,
              "skipped": false
            },
            {
              "title": "Validação de erro: CNPJ do Transportador (vazio) ou (inválido)",
              "fullTitle": "Integração Clientes - API Inclusão de Ficha do Profissional - Validação de Erros Validação de erro: CNPJ do Transportador (vazio) ou (inválido)",
              "timedOut": null,
              "duration": 4809,
              "state": "passed",
              "speed": "fast",
              "pass": true,
              "fail": false,
              "pending": false,
              "context": null,
              "code": "const cnpj = [\"abc\"];\nconst payloadModificado = soapPayload.replace(`<inc:cnpj_transportador>${cnpjTransportador}</inc:cnpj_transportador>`, ` <inc:cnpj_transportador>${cnpj}</inc:cnpj_transportador>`);\ncy.api({\n  method: \"POST\",\n  url: url,\n  body: payloadModificado,\n  failOnStatusCode: false\n}).then(r => {\n  const faultcode = r.body.match(/<faultcode>([\\s\\S]*?)<\\/faultcode>/)[1].trim();\n  const faultstring = r.body.match(/<faultstring>([\\s\\S]*?)<\\/faultstring>/)[1].trim();\n  expect(r.status).to.eq(500);\n  expect(faultcode).to.eq(\"ns1:1\");\n  expect(faultstring).to.be.oneOf([\"O CNPJ Transportador não informado ou XML Inválido\", \"O CNPJ Transportador não está cadastrado\"]);\n});",
              "err": {},
              "uuid": "cc30e777-6978-4cbb-96e8-be14c2e94044",
              "parentUUID": "d58f4515-5972-4e0f-a4d7-e64371ac87b3",
              "isHook": false,
              "skipped": false
            },
            {
              "title": "Validação de erro: Foto do profissional (vazio)",
              "fullTitle": "Integração Clientes - API Inclusão de Ficha do Profissional - Validação de Erros Validação de erro: Foto do profissional (vazio)",
              "timedOut": null,
              "duration": 3849,
              "state": "passed",
              "speed": "fast",
              "pass": true,
              "fail": false,
              "pending": false,
              "context": null,
              "code": "const payloadModificado = soapPayload.replace(`${imagemBase64}`, \"\");\ncy.api({\n  method: \"POST\",\n  url: url,\n  body: payloadModificado,\n  failOnStatusCode: false\n}).then(r => {\n  const faultcode = r.body.match(/<faultcode>([\\s\\S]*?)<\\/faultcode>/)[1].trim();\n  const faultstring = r.body.match(/<faultstring>([\\s\\S]*?)<\\/faultstring>/)[1].trim();\n  expect(r.status).to.eq(500);\n  expect(faultcode).to.eq(\"ns1:1\");\n  expect(faultstring).to.eq(\"Foto Profissional não informado\");\n});",
              "err": {},
              "uuid": "0eeb36ea-7f78-434b-981b-950c1f39d99d",
              "parentUUID": "d58f4515-5972-4e0f-a4d7-e64371ac87b3",
              "isHook": false,
              "skipped": false
            },
            {
              "title": "Validação de erro: Foto do profissional (maior que 5MB)",
              "fullTitle": "Integração Clientes - API Inclusão de Ficha do Profissional - Validação de Erros Validação de erro: Foto do profissional (maior que 5MB)",
              "timedOut": null,
              "duration": 14578,
              "state": "passed",
              "speed": "slow",
              "pass": true,
              "fail": false,
              "pending": false,
              "context": null,
              "code": "const payloadModificado = soapPayload.replace(`${imagemBase64}`, `${imagemBase64_5MB}`);\ncy.api({\n  method: \"POST\",\n  url: url,\n  body: payloadModificado,\n  failOnStatusCode: false\n}).then(r => {\n  const faultcode = r.body.match(/<faultcode>([\\s\\S]*?)<\\/faultcode>/)[1].trim();\n  const faultstring = r.body.match(/<faultstring>([\\s\\S]*?)<\\/faultstring>/)[1].trim();\n  expect(r.status).to.eq(500);\n  expect(faultcode).to.eq(\"ns1:1\");\n  expect(faultstring).to.eq(\"Foto Profissional, a imagem deve ter no máximo 5MB.\");\n});",
              "err": {},
              "uuid": "3f4d4725-c832-449f-9fe0-5c8f1683ea47",
              "parentUUID": "d58f4515-5972-4e0f-a4d7-e64371ac87b3",
              "isHook": false,
              "skipped": false
            },
            {
              "title": "Validação de erro: Documento do profissional (vazio) ou (inválido)",
              "fullTitle": "Integração Clientes - API Inclusão de Ficha do Profissional - Validação de Erros Validação de erro: Documento do profissional (vazio) ou (inválido)",
              "timedOut": null,
              "duration": 4421,
              "state": "passed",
              "speed": "fast",
              "pass": true,
              "fail": false,
              "pending": false,
              "context": null,
              "code": "const documento = [\"\", \"123456789\"];\nconst docAleatorio = documento[Math.floor(Math.random() * documento.length)];\nconst payloadModificado = soapPayload.replace(`<inc:documento>${cpfAleatorio}</inc:documento>`, `<inc:documento>${docAleatorio}</inc:documento>`);\ncy.api({\n  method: \"POST\",\n  url: url,\n  body: payloadModificado,\n  failOnStatusCode: false\n}).then(r => {\n  const faultcode = r.body.match(/<faultcode>([\\s\\S]*?)<\\/faultcode>/)[1].trim();\n  const faultstring = r.body.match(/<faultstring>([\\s\\S]*?)<\\/faultstring>/)[1].trim();\n  expect(r.status).to.eq(500);\n  expect(faultcode).to.eq(\"ns1:1\");\n  expect(faultstring).to.be.oneOf([\"CPF profissional não informado\", \"O CPF do profissional é inválido\"]);\n});",
              "err": {},
              "uuid": "a0e00db2-2c90-4d70-9f77-6a548f8ecb6c",
              "parentUUID": "d58f4515-5972-4e0f-a4d7-e64371ac87b3",
              "isHook": false,
              "skipped": false
            }
          ],
          "suites": [],
          "passes": [
            "3daeeca4-d420-48ea-9655-cdb37593c84c",
            "76808a4c-733d-409c-a85c-8c1e56d6be99",
            "c4de8bba-3816-4b0f-9b4f-a003d311791f",
            "cc30e777-6978-4cbb-96e8-be14c2e94044",
            "0eeb36ea-7f78-434b-981b-950c1f39d99d",
            "3f4d4725-c832-449f-9fe0-5c8f1683ea47",
            "a0e00db2-2c90-4d70-9f77-6a548f8ecb6c"
          ],
          "failures": [],
          "pending": [],
          "skipped": [],
          "duration": 37092,
          "root": false,
          "rootEmpty": false,
          "_timeout": 2000
        }
      ],
      "passes": [],
      "failures": [],
      "pending": [],
      "skipped": [],
      "duration": 0,
      "root": true,
      "rootEmpty": true,
      "_timeout": 2000
    }
  ],
  "meta": {
    "mocha": {
      "version": "7.2.0"
    },
    "mochawesome": {
      "options": {
        "quiet": false,
        "reportFilename": "[name]-report",
        "saveHtml": true,
        "saveJson": true,
        "consoleReporter": "spec",
        "useInlineDiffs": false,
        "code": true
      },
      "version": "7.1.4"
    },
    "marge": {
      "options": {
        "reportDir": "cypress/results",
        "overwrite": false,
        "html": true,
        "json": true,
        "reportFilename": "[name]-report"
      },
      "version": "6.3.0"
    }
  }
}